pyscfadlib/BUILD
pyscfadlib/CMakeLists.txt
pyscfadlib/__init__.py
pyscfadlib/apply_patch.sh
pyscfadlib/config.h
pyscfadlib/config.h.in
pyscfadlib/ffi_helpers.h
pyscfadlib/gpu_solver.py
pyscfadlib/kernel_nanobind_helpers.h
pyscfadlib/lapack.py
pyscfadlib/lib.py
pyscfadlib/libao2mo_vjp.so
pyscfadlib/libcc_vjp.so
pyscfadlib/libcgto_ad.so
pyscfadlib/libcgto_vjp.so
pyscfadlib/libcint.patch
pyscfadlib/libcint.patch.5.4
pyscfadlib/libcint.patch.6.1
pyscfadlib/libcvhf_vjp.so
pyscfadlib/libnp_helper_ad.so
pyscfadlib/libnp_helper_vjp.so
pyscfadlib/libvjp_util.so
pyscfadlib/pyscfad.bzl
pyscfadlib/pyscfad_lapack.cpython-311-aarch64-linux-gnu.so
pyscfadlib/version.py
pyscfadlib/cuda/BUILD
pyscfadlib/cuda/solver.cc
pyscfadlib/cuda/solver_kernels.cc
pyscfadlib/cuda/solver_kernels.h
pyscfadlib/cuda/vendor.h
pyscfadlib/gto/CMakeLists.txt
pyscfadlib/gto/deriv1.c
pyscfadlib/gto/deriv2.c
pyscfadlib/gto/fastexp.c
pyscfadlib/gto/fill_grids_int2c.c
pyscfadlib/gto/fill_int2c.c
pyscfadlib/gto/fill_int2e.c
pyscfadlib/gto/fill_nr_3c.c
pyscfadlib/gto/fill_r_3c.c
pyscfadlib/gto/fill_r_4c.c
pyscfadlib/gto/ft_ao.c
pyscfadlib/gto/ft_ao.h
pyscfadlib/gto/ft_ao_deriv.c
pyscfadlib/gto/grid_ao_drv.c
pyscfadlib/gto/grid_ao_drv.h
pyscfadlib/gto/gto.h
pyscfadlib/gto/nr_ecp.c
pyscfadlib/gto/nr_ecp.h
pyscfadlib/gto/nr_ecp_deriv.c
pyscfadlib/gto/autocode/auto_eval.cl
pyscfadlib/gto/autocode/auto_eval1.c
pyscfadlib/gto/autocode/derivator.cl
pyscfadlib/gto/autocode/gen-code.cl
pyscfadlib/gto/autocode/parser.cl
pyscfadlib/gto/autocode/utility.cl
pyscfadlib/gto/test/test_ecp.py
pyscfadlib/gto/test/test_gridao.py
pyscfadlib/lapack/CMakeLists.txt
pyscfadlib/lapack/lapack.cc
pyscfadlib/lapack/lapack_kernels.cc
pyscfadlib/lapack/lapack_kernels.h
pyscfadlib/np_helper/CMakeLists.txt
pyscfadlib/np_helper/np_helper.c
pyscfadlib/np_helper/np_helper.h
pyscfadlib/np_helper/pack_tril.c
pyscfadlib/thirdparty/include/cint.h
pyscfadlib-0.2.0.dist-info/METADATA
pyscfadlib-0.2.0.dist-info/WHEEL
pyscfadlib-0.2.0.dist-info/RECORD
pyscfadlib-0.2.0.dist-info/licenses/LICENSE
pyscfadlib-0.2.0.dist-info/sboms/auditwheel.cdx.json
